jupyter_sphinx_theme/__init__.py
jupyter_sphinx_theme/jupyter/globaltoc.html
jupyter_sphinx_theme/jupyter/layout.html
jupyter_sphinx_theme/jupyter/localtoc.html
jupyter_sphinx_theme/jupyter/navbar-2.html
jupyter_sphinx_theme/jupyter/navbar.html
jupyter_sphinx_theme/jupyter/navbarsearchbox.html
jupyter_sphinx_theme/jupyter/navbartoc.html
jupyter_sphinx_theme/jupyter/relations.html
jupyter_sphinx_theme/jupyter/search.html
jupyter_sphinx_theme/jupyter/searchbox.html
jupyter_sphinx_theme/jupyter/searchresults.html
jupyter_sphinx_theme/jupyter/sidebartoc.html
jupyter_sphinx_theme/jupyter/sourcelink.html
jupyter_sphinx_theme/jupyter/theme.conf
jupyter_sphinx_theme/jupyter/static/bootstrap-sphinx.css_t
jupyter_sphinx_theme/jupyter/static/bootstrap-sphinx.js_t
jupyter_sphinx_theme/jupyter/static/bootstrap-2.3.2/css/bootstrap-responsive.css
jupyter_sphinx_theme/jupyter/static/bootstrap-2.3.2/css/bootstrap-responsive.min.css
jupyter_sphinx_theme/jupyter/static/bootstrap-2.3.2/css/bootstrap.css
jupyter_sphinx_theme/jupyter/static/bootstrap-2.3.2/css/bootstrap.min.css
jupyter_sphinx_theme/jupyter/static/bootstrap-2.3.2/img/glyphicons-halflings-white.png
jupyter_sphinx_theme/jupyter/static/bootstrap-2.3.2/img/glyphicons-halflings.png
jupyter_sphinx_theme/jupyter/static/bootstrap-2.3.2/js/bootstrap.js
jupyter_sphinx_theme/jupyter/static/bootstrap-2.3.2/js/bootstrap.min.js
jupyter_sphinx_theme/jupyter/static/bootstrap-3.3.4/css/bootstrap-theme.css
jupyter_sphinx_theme/jupyter/static/bootstrap-3.3.4/css/bootstrap-theme.css.map
jupyter_sphinx_theme/jupyter/static/bootstrap-3.3.4/css/bootstrap-theme.min.css
jupyter_sphinx_theme/jupyter/static/bootstrap-3.3.4/css/bootstrap.css
jupyter_sphinx_theme/jupyter/static/bootstrap-3.3.4/css/bootstrap.css.map
jupyter_sphinx_theme/jupyter/static/bootstrap-3.3.4/css/bootstrap.min.css
jupyter_sphinx_theme/jupyter/static/bootstrap-3.3.4/fonts/glyphicons-halflings-regular.eot
jupyter_sphinx_theme-0.0.6.dist-info/DESCRIPTION.rst
jupyter_sphinx_theme-0.0.6.dist-info/METADATA
jupyter_sphinx_theme-0.0.6.dist-info/RECORD
jupyter_sphinx_theme-0.0.6.dist-info/WHEEL
jupyter_sphinx_theme-0.0.6.dist-info/metadata.json
jupyter_sphinx_theme-0.0.6.dist-info/top_level.txt
