Metadata-Version: 2.0
Name: jupyter-sphinx-theme
Version: 0.0.6
Summary: Jupyter Sphinx Theme.
Home-page: http://github.com/jupyter/sphinx-theme
Author: Ryan Roemer, Project Jupyter, and contributors
Author-email: jupyter@googlegroups.com
License: UNKNOWN
Platform: UNKNOWN
Classifier: Development Status :: 5 - Production/Stable
Classifier: Environment :: Web Environment
Classifier: Intended Audience :: Developers
Classifier: Intended Audience :: System Administrators
Classifier: License :: OSI Approved :: MIT License
Classifier: Operating System :: OS Independent
Classifier: Programming Language :: Python
Classifier: Topic :: Internet
Classifier: Topic :: Software Development :: Documentation
Requires-Dist: nbsphinx
Requires-Dist: recommonmark (==0.4.0)
Requires-Dist: setuptools
